paypal_subscription/__init__.py
paypal_subscription/paypal.py
paypal_subscription-0.1.2.dist-info/licenses/LICENSE
paypal_subscription-0.1.2.dist-info/METADATA
paypal_subscription-0.1.2.dist-info/WHEEL
paypal_subscription-0.1.2.dist-info/top_level.txt
paypal_subscription-0.1.2.dist-info/RECORD
