Metadata-Version: 2.4
Name: paypal-subscription
Version: 0.1.2
Summary: This Python library allows you to interact with the PayPal REST API to manage subscriptions with variable pricing. It includes functionality for creating, updating, suspend and verifying subscriptions, as well as managing products and plans.
Home-page: https://github.com/CodeAtCode/paypal-subscription-lib
Author: Codeat
Author-email: mte90net@gmail.com
Classifier: Programming Language :: Python :: 3
Classifier: License :: OSI Approved :: MIT License
Classifier: Operating System :: OS Independent
Requires-Python: >=3.11
License-File: LICENSE
Dynamic: author
Dynamic: author-email
Dynamic: classifier
Dynamic: description
Dynamic: description-content-type
Dynamic: home-page
Dynamic: license-file
Dynamic: requires-python
Dynamic: summary
